boolean/__init__.py
boolean/boolean.py
boolean/test_boolean.py
boolean.py-3.7.dist-info/LICENSE.txt
boolean.py-3.7.dist-info/METADATA
boolean.py-3.7.dist-info/WHEEL
boolean.py-3.7.dist-info/top_level.txt
boolean.py-3.7.dist-info/RECORD
