Metadata-Version: 1.1
Name: boolean.py
Version: 3.7
Summary: Define boolean algebras, create and parse boolean expressions and create custom boolean DSL.
Home-page: https://github.com/bastikr/boolean.py
Author: Sebastian Kraemer
Author-email: basti.kr@gmail.com
License: BSD-2-Clause
Keywords: boolean expression,boolean algebra,logic,expression parser
Platform: UNKNOWN
Classifier: Development Status :: 5 - Production/Stable
Classifier: Intended Audience :: Developers
Classifier: Operating System :: OS Independent
Classifier: Programming Language :: Python
Classifier: Programming Language :: Python :: 2.7
Classifier: Programming Language :: Python :: 3
Classifier: Topic :: Scientific/Engineering :: Mathematics
Classifier: Topic :: Software Development :: Compilers
Classifier: Topic :: Software Development :: Libraries
Classifier: Topic :: Utilities
